tests/__init__.py
tests/v1/__init__.py
to_literal/__init__.py
to_literal/v1/__init__.py
to_literal/v1/castLiteral.py
to_literal-1.1.2.dist-info/METADATA
to_literal-1.1.2.dist-info/WHEEL
to_literal-1.1.2.dist-info/top_level.txt
to_literal-1.1.2.dist-info/RECORD
